.gitignore
.travis.yml
CHANGES.rst
CONTRIBUTORS.rst
README.rst
bootstrap.py
buildout.cfg
setup.cfg
setup.py
travis.cfg
docs/LICENSE.GPL
docs/LICENSE.txt
src/collective/__init__.py
src/collective.behavior.localanalytics.egg-info/PKG-INFO
src/collective.behavior.localanalytics.egg-info/SOURCES.txt
src/collective.behavior.localanalytics.egg-info/dependency_links.txt
src/collective.behavior.localanalytics.egg-info/entry_points.txt
src/collective.behavior.localanalytics.egg-info/namespace_packages.txt
src/collective.behavior.localanalytics.egg-info/not-zip-safe
src/collective.behavior.localanalytics.egg-info/requires.txt
src/collective.behavior.localanalytics.egg-info/top_level.txt
src/collective/behavior/__init__.py
src/collective/behavior/localanalytics/__init__.py
src/collective/behavior/localanalytics/analytics.py
src/collective/behavior/localanalytics/behavior.py
src/collective/behavior/localanalytics/configure.zcml
src/collective/behavior/localanalytics/testing.py
src/collective/behavior/localanalytics/browser/__init__.py
src/collective/behavior/localanalytics/browser/configure.zcml
src/collective/behavior/localanalytics/browser/view.py
src/collective/behavior/localanalytics/locales/README.txt
src/collective/behavior/localanalytics/tests/__init__.py
src/collective/behavior/localanalytics/tests/test_behavior.py