Metadata-Version: 1.0
Name: collective.behavior.localanalytics
Version: 1.0
Summary: Dexterity behavior to enable local Analytics settings
Home-page: https://github.com/collective/collective.behavior.localanalytics
Author: David Beitey
Author-email: python@davidjb.com
License: gpl
Keywords: dexterity behavior analytics plone
Platform: UNKNOWN
Classifier: Framework :: Plone
Classifier: Programming Language :: Python
Classifier: Topic :: Software Development :: Libraries :: Python Modules
